egl/__init__.py
egl/alg_optimizer.py
egl/cma.py
egl/convergence.py
egl/datsets.py
egl/distribution.py
egl/egl.py
egl/exception.py
egl/function.py
egl/handlers.py
egl/igl.py
egl/losses.py
egl/stop_condition.py
egl/trainer.py
egl/trust_region.py
egl/utils.py
egl/value_normalizer.py
bbo_egl-1.1.0.dist-info/METADATA
bbo_egl-1.1.0.dist-info/WHEEL
bbo_egl-1.1.0.dist-info/licenses/LICENSE
bbo_egl-1.1.0.dist-info/RECORD
