Metadata-Version: 2.4
Name: bbo-egl
Version: 1.1.0
Summary: A package of black-box optimization (BBO) algorithms.
License: MIT
License-File: LICENSE
Author: Yedidya Kfir
Author-email: yedidyakfir@gmail.com
Requires-Python: >=3.10,<4.0
Classifier: License :: OSI Approved :: MIT License
Classifier: Programming Language :: Python :: 3
Classifier: Programming Language :: Python :: 3.10
Classifier: Programming Language :: Python :: 3.11
Classifier: Programming Language :: Python :: 3.12
Classifier: Programming Language :: Python :: 3.13
Classifier: Programming Language :: Python :: 3.14
Provides-Extra: cma
Requires-Dist: torch
Requires-Dist: tqdm
